{
    "id": 115010600,
    "name": "Retro Adventure",
    "author": "SpectricGMD",
    "creators": ["SpectricGMD"],
    "verifier": "SpectricGMD",
    "verification": "https://www.youtube.com/watch?v=YkIqFYqXhVE",
    "showcase": "https://youtu.be/8K0vq-dw_gU",
    "password": "Free Copy",
    "percentToQualify": 63,
    "records": [
        {
            "user": "Gp0",
            "link": "https://www.youtube.com/watch?v=RbtpK0YHBpc",
            "percent": 100,
            "hz": "CBF"
        },
        {
            "user": "Z",
            "link": "https://youtu.be/TmMM9lLztN4",
            "percent": 100,
            "hz": "240"
        }
    ]
}
